ecfas/__init__.py
ecfas/check_trigger.py
ecfas/cmems_datasets.py
ecfas/cmems_operational_fullworkflow.py
ecfas/cmems_operational_validate.py
ecfas/coast_water_level_extract_multiple.py
ecfas/coast_water_level_process.py
ecfas/coast_water_level_trigger.py
ecfas/coast_water_level_validate.py
ecfas/download_insitu_obs.py
ecfas/functions_trigger.py
ecfas/mds_download.py
ecfas/quality_checks.py
ecfas/swash_formulations.py
ecfas/utils.py
ecfas/version.py
ecfas/fes/__init__.py
ecfas/fes/load_tide.ini
ecfas/fes/module_FES2014.py
ecfas/fes/ocean_tide.ini
ecfas/fes/ocean_tide_extrapolated.ini
ecfas/output_points/output_locs_ARC.txt
ecfas/output_points/output_locs_ARC_ocean.txt
ecfas/output_points/output_locs_BAL.txt
ecfas/output_points/output_locs_BS.txt
ecfas/output_points/output_locs_GLO.txt
ecfas/output_points/output_locs_IBI.txt
ecfas/output_points/output_locs_MED.txt
ecfas/output_points/output_locs_NWS.txt
ecfas/thresholds/EU_EVATWLWS_PCT97.csv
ecfas/thresholds/ThresholdsFile.csv
ecfas-2.0.0.dist-info/licenses/LICENCE
ecfas-2.0.0.dist-info/METADATA
ecfas-2.0.0.dist-info/WHEEL
ecfas-2.0.0.dist-info/entry_points.txt
ecfas-2.0.0.dist-info/top_level.txt
ecfas-2.0.0.dist-info/RECORD
