Metadata-Version: 2.4
Name: ecfas
Version: 2.0.0
Home-page: https://gitlab.mercator-ocean.fr/mirazoki/ecfas
Author: Maialen Irazoki
Author-email: mirazoki@mercator-ocean.fr
License: BSD Licence
Project-URL: Repository, https://gitlab.mercator-ocean.fr/mirazoki/ecfas
Classifier: Development Status :: 4 - Beta
Classifier: Intended Audience :: Science/Research
Classifier: Topic :: Scientific/Engineering
Classifier: Environment :: Console
Classifier: Programming Language :: Python :: 3.10
Classifier: License :: OSI Approved :: BSD License
Requires-Python: >=3.10,<3.11
License-File: LICENCE
Requires-Dist: copernicusmarine==2.0.1
Requires-Dist: configobj==5.0.6
Dynamic: author
Dynamic: author-email
Dynamic: classifier
Dynamic: description
Dynamic: description-content-type
Dynamic: home-page
Dynamic: license
Dynamic: license-file
Dynamic: project-url
Dynamic: requires-dist
Dynamic: requires-python
